startings/__init__.py
startings/__init__.pyi
startings/windows.py
startings-0.1.0.dist-info/METADATA
startings-0.1.0.dist-info/WHEEL
startings-0.1.0.dist-info/RECORD
