Metadata-Version: 2.1
Name: startings
Version: 0.1.0
Summary: Register python scripts as bootstrapped
Author: jawide
Author-email: 596929059@qq.com
Requires-Python: >=3.7
Classifier: Programming Language :: Python :: 3
Classifier: Programming Language :: Python :: 3.7
Classifier: Programming Language :: Python :: 3.8
Classifier: Programming Language :: Python :: 3.9
Classifier: Programming Language :: Python :: 3.10
Classifier: Programming Language :: Python :: 3.11
Requires-Dist: daemonprocessing (>=0.1.3,<0.2.0)
